<?xml version="1.0" encoding="utf-8"?>
<Document>
  <Engineering version="V17" />
  <DocumentInfo>
    <Created>2024-08-20T13:26:12.2605555Z</Created>
    <ExportSetting>WithDefaults</ExportSetting>
    <InstalledProducts>
      <Product>
        <DisplayName>Totally Integrated Automation Portal</DisplayName>
        <DisplayVersion>V17 Update 4</DisplayVersion>
      </Product>
      <OptionPackage>
        <DisplayName>TIA Portal Openness</DisplayName>
        <DisplayVersion>V17 Update 4</DisplayVersion>
      </OptionPackage>
      <OptionPackage>
        <DisplayName>TIA Portal Version Control Interface</DisplayName>
        <DisplayVersion>V17</DisplayVersion>
      </OptionPackage>
      <Product>
        <DisplayName>STEP 7 Professional</DisplayName>
        <DisplayVersion>V17 Update 4</DisplayVersion>
      </Product>
      <OptionPackage>
        <DisplayName>STEP 7 Safety</DisplayName>
        <DisplayVersion>V17</DisplayVersion>
      </OptionPackage>
      <Product>
        <DisplayName>WinCC Advanced</DisplayName>
        <DisplayVersion>V17 Update 4</DisplayVersion>
      </Product>
    </InstalledProducts>
  </DocumentInfo>
  <SW.Blocks.InstanceDB ID="0">
    <AttributeList>
      <AutoNumber>false</AutoNumber>
      <DBAccessibleFromOPCUA>true</DBAccessibleFromOPCUA>
      <HeaderAuthor />
      <HeaderFamily />
      <HeaderName />
      <HeaderVersion>0.1</HeaderVersion>
      <InstanceOfName>MODBUS</InstanceOfName>
      <InstanceOfType>FB</InstanceOfType>
      <Interface><Sections xmlns="http://www.siemens.com/automation/Openness/SW/Interface/v5">
  <Section Name="Input" />
  <Section Name="Output" />
  <Section Name="InOut" />
  <Section Name="Static">
    <Member Name="TEFC0" Datatype="TON_TIME" Version="1.0" Remanence="NonRetain" Accessibility="Public"><AttributeList><BooleanAttribute Name="ExternalAccessible" SystemDefined="true">true</BooleanAttribute><BooleanAttribute Name="ExternalVisible" SystemDefined="true">true</BooleanAttribute><BooleanAttribute Name="ExternalWritable" SystemDefined="true">true</BooleanAttribute><BooleanAttribute Name="SetPoint" SystemDefined="true">true</BooleanAttribute></AttributeList><Sections><Section Name="None"><Member Name="PT" Datatype="Time" /><Member Name="ET" Datatype="Time" /><Member Name="IN" Datatype="Bool" /><Member Name="Q" Datatype="Bool" /></Section></Sections></Member>
    <Member Name="INI_MOD" Datatype="TON_TIME" Version="1.0" Remanence="NonRetain" Accessibility="Public"><AttributeList><BooleanAttribute Name="ExternalAccessible" SystemDefined="true">true</BooleanAttribute><BooleanAttribute Name="ExternalVisible" SystemDefined="true">true</BooleanAttribute><BooleanAttribute Name="ExternalWritable" SystemDefined="true">true</BooleanAttribute><BooleanAttribute Name="SetPoint" SystemDefined="true">true</BooleanAttribute></AttributeList><Sections><Section Name="None"><Member Name="PT" Datatype="Time" /><Member Name="ET" Datatype="Time" /><Member Name="IN" Datatype="Bool" /><Member Name="Q" Datatype="Bool" /></Section></Sections></Member>
    <Member Name="TEFC1" Datatype="TON_TIME" Version="1.0" Remanence="NonRetain" Accessibility="Public"><AttributeList><BooleanAttribute Name="ExternalAccessible" SystemDefined="true">true</BooleanAttribute><BooleanAttribute Name="ExternalVisible" SystemDefined="true">true</BooleanAttribute><BooleanAttribute Name="ExternalWritable" SystemDefined="true">true</BooleanAttribute><BooleanAttribute Name="SetPoint" SystemDefined="true">true</BooleanAttribute></AttributeList><Sections><Section Name="None"><Member Name="PT" Datatype="Time" /><Member Name="ET" Datatype="Time" /><Member Name="IN" Datatype="Bool" /><Member Name="Q" Datatype="Bool" /></Section></Sections></Member>
    <Member Name="TEFC2" Datatype="TON_TIME" Version="1.0" Remanence="NonRetain" Accessibility="Public"><AttributeList><BooleanAttribute Name="ExternalAccessible" SystemDefined="true">true</BooleanAttribute><BooleanAttribute Name="ExternalVisible" SystemDefined="true">true</BooleanAttribute><BooleanAttribute Name="ExternalWritable" SystemDefined="true">true</BooleanAttribute><BooleanAttribute Name="SetPoint" SystemDefined="true">true</BooleanAttribute></AttributeList><Sections><Section Name="None"><Member Name="PT" Datatype="Time" /><Member Name="ET" Datatype="Time" /><Member Name="IN" Datatype="Bool" /><Member Name="Q" Datatype="Bool" /></Section></Sections></Member>
    <Member Name="TEFC3" Datatype="TON_TIME" Version="1.0" Remanence="NonRetain" Accessibility="Public"><AttributeList><BooleanAttribute Name="ExternalAccessible" SystemDefined="true">true</BooleanAttribute><BooleanAttribute Name="ExternalVisible" SystemDefined="true">true</BooleanAttribute><BooleanAttribute Name="ExternalWritable" SystemDefined="true">true</BooleanAttribute><BooleanAttribute Name="SetPoint" SystemDefined="true">true</BooleanAttribute></AttributeList><Sections><Section Name="None"><Member Name="PT" Datatype="Time" /><Member Name="ET" Datatype="Time" /><Member Name="IN" Datatype="Bool" /><Member Name="Q" Datatype="Bool" /></Section></Sections></Member>
    <Member Name="TEFC4" Datatype="TON_TIME" Version="1.0" Remanence="NonRetain" Accessibility="Public"><AttributeList><BooleanAttribute Name="ExternalAccessible" SystemDefined="true">true</BooleanAttribute><BooleanAttribute Name="ExternalVisible" SystemDefined="true">true</BooleanAttribute><BooleanAttribute Name="ExternalWritable" SystemDefined="true">true</BooleanAttribute><BooleanAttribute Name="SetPoint" SystemDefined="true">true</BooleanAttribute></AttributeList><Sections><Section Name="None"><Member Name="PT" Datatype="Time" /><Member Name="ET" Datatype="Time" /><Member Name="IN" Datatype="Bool" /><Member Name="Q" Datatype="Bool" /></Section></Sections></Member>
    <Member Name="TEFC5" Datatype="TON_TIME" Version="1.0" Remanence="NonRetain" Accessibility="Public"><AttributeList><BooleanAttribute Name="ExternalAccessible" SystemDefined="true">true</BooleanAttribute><BooleanAttribute Name="ExternalVisible" SystemDefined="true">true</BooleanAttribute><BooleanAttribute Name="ExternalWritable" SystemDefined="true">true</BooleanAttribute><BooleanAttribute Name="SetPoint" SystemDefined="true">true</BooleanAttribute></AttributeList><Sections><Section Name="None"><Member Name="PT" Datatype="Time" /><Member Name="ET" Datatype="Time" /><Member Name="IN" Datatype="Bool" /><Member Name="Q" Datatype="Bool" /></Section></Sections></Member>
    <Member Name="TEFC6" Datatype="TON_TIME" Version="1.0" Remanence="NonRetain" Accessibility="Public"><AttributeList><BooleanAttribute Name="ExternalAccessible" SystemDefined="true">true</BooleanAttribute><BooleanAttribute Name="ExternalVisible" SystemDefined="true">true</BooleanAttribute><BooleanAttribute Name="ExternalWritable" SystemDefined="true">true</BooleanAttribute><BooleanAttribute Name="SetPoint" SystemDefined="true">true</BooleanAttribute></AttributeList><Sections><Section Name="None"><Member Name="PT" Datatype="Time" /><Member Name="ET" Datatype="Time" /><Member Name="IN" Datatype="Bool" /><Member Name="Q" Datatype="Bool" /></Section></Sections></Member>
    <Member Name="TEFC7" Datatype="TON_TIME" Version="1.0" Remanence="NonRetain" Accessibility="Public"><AttributeList><BooleanAttribute Name="ExternalAccessible" SystemDefined="true">true</BooleanAttribute><BooleanAttribute Name="ExternalVisible" SystemDefined="true">true</BooleanAttribute><BooleanAttribute Name="ExternalWritable" SystemDefined="true">true</BooleanAttribute><BooleanAttribute Name="SetPoint" SystemDefined="true">true</BooleanAttribute></AttributeList><Sections><Section Name="None"><Member Name="PT" Datatype="Time" /><Member Name="ET" Datatype="Time" /><Member Name="IN" Datatype="Bool" /><Member Name="Q" Datatype="Bool" /></Section></Sections></Member>
    <Member Name="TEFC8" Datatype="TON_TIME" Version="1.0" Remanence="NonRetain" Accessibility="Public"><AttributeList><BooleanAttribute Name="ExternalAccessible" SystemDefined="true">true</BooleanAttribute><BooleanAttribute Name="ExternalVisible" SystemDefined="true">true</BooleanAttribute><BooleanAttribute Name="ExternalWritable" SystemDefined="true">true</BooleanAttribute><BooleanAttribute Name="SetPoint" SystemDefined="true">true</BooleanAttribute></AttributeList><Sections><Section Name="None"><Member Name="PT" Datatype="Time" /><Member Name="ET" Datatype="Time" /><Member Name="IN" Datatype="Bool" /><Member Name="Q" Datatype="Bool" /></Section></Sections></Member>
    <Member Name="TEFC9" Datatype="TON_TIME" Version="1.0" Remanence="NonRetain" Accessibility="Public"><AttributeList><BooleanAttribute Name="ExternalAccessible" SystemDefined="true">true</BooleanAttribute><BooleanAttribute Name="ExternalVisible" SystemDefined="true">true</BooleanAttribute><BooleanAttribute Name="ExternalWritable" SystemDefined="true">true</BooleanAttribute><BooleanAttribute Name="SetPoint" SystemDefined="true">true</BooleanAttribute></AttributeList><Sections><Section Name="None"><Member Name="PT" Datatype="Time" /><Member Name="ET" Datatype="Time" /><Member Name="IN" Datatype="Bool" /><Member Name="Q" Datatype="Bool" /></Section></Sections></Member>
    <Member Name="TEFC10" Datatype="TON_TIME" Version="1.0" Remanence="NonRetain" Accessibility="Public"><AttributeList><BooleanAttribute Name="ExternalAccessible" SystemDefined="true">true</BooleanAttribute><BooleanAttribute Name="ExternalVisible" SystemDefined="true">true</BooleanAttribute><BooleanAttribute Name="ExternalWritable" SystemDefined="true">true</BooleanAttribute><BooleanAttribute Name="SetPoint" SystemDefined="true">true</BooleanAttribute></AttributeList><Sections><Section Name="None"><Member Name="PT" Datatype="Time" /><Member Name="ET" Datatype="Time" /><Member Name="IN" Datatype="Bool" /><Member Name="Q" Datatype="Bool" /></Section></Sections></Member>
    <Member Name="TEFC11" Datatype="TON_TIME" Version="1.0" Remanence="NonRetain" Accessibility="Public"><AttributeList><BooleanAttribute Name="ExternalAccessible" SystemDefined="true">true</BooleanAttribute><BooleanAttribute Name="ExternalVisible" SystemDefined="true">true</BooleanAttribute><BooleanAttribute Name="ExternalWritable" SystemDefined="true">true</BooleanAttribute><BooleanAttribute Name="SetPoint" SystemDefined="true">true</BooleanAttribute></AttributeList><Sections><Section Name="None"><Member Name="PT" Datatype="Time" /><Member Name="ET" Datatype="Time" /><Member Name="IN" Datatype="Bool" /><Member Name="Q" Datatype="Bool" /></Section></Sections></Member>
    <Member Name="TEFC12" Datatype="TON_TIME" Version="1.0" Remanence="NonRetain" Accessibility="Public"><AttributeList><BooleanAttribute Name="ExternalAccessible" SystemDefined="true">true</BooleanAttribute><BooleanAttribute Name="ExternalVisible" SystemDefined="true">true</BooleanAttribute><BooleanAttribute Name="ExternalWritable" SystemDefined="true">true</BooleanAttribute><BooleanAttribute Name="SetPoint" SystemDefined="true">true</BooleanAttribute></AttributeList><Sections><Section Name="None"><Member Name="PT" Datatype="Time" /><Member Name="ET" Datatype="Time" /><Member Name="IN" Datatype="Bool" /><Member Name="Q" Datatype="Bool" /></Section></Sections></Member>
    <Member Name="TEFC13" Datatype="TON_TIME" Version="1.0" Remanence="NonRetain" Accessibility="Public"><AttributeList><BooleanAttribute Name="ExternalAccessible" SystemDefined="true">true</BooleanAttribute><BooleanAttribute Name="ExternalVisible" SystemDefined="true">true</BooleanAttribute><BooleanAttribute Name="ExternalWritable" SystemDefined="true">true</BooleanAttribute><BooleanAttribute Name="SetPoint" SystemDefined="true">true</BooleanAttribute></AttributeList><Sections><Section Name="None"><Member Name="PT" Datatype="Time" /><Member Name="ET" Datatype="Time" /><Member Name="IN" Datatype="Bool" /><Member Name="Q" Datatype="Bool" /></Section></Sections></Member>
    <Member Name="TEFC14" Datatype="TON_TIME" Version="1.0" Remanence="NonRetain" Accessibility="Public"><AttributeList><BooleanAttribute Name="ExternalAccessible" SystemDefined="true">true</BooleanAttribute><BooleanAttribute Name="ExternalVisible" SystemDefined="true">true</BooleanAttribute><BooleanAttribute Name="ExternalWritable" SystemDefined="true">true</BooleanAttribute><BooleanAttribute Name="SetPoint" SystemDefined="true">true</BooleanAttribute></AttributeList><Sections><Section Name="None"><Member Name="PT" Datatype="Time" /><Member Name="ET" Datatype="Time" /><Member Name="IN" Datatype="Bool" /><Member Name="Q" Datatype="Bool" /></Section></Sections></Member>
    <Member Name="TEFC15" Datatype="TON_TIME" Version="1.0" Remanence="NonRetain" Accessibility="Public"><AttributeList><BooleanAttribute Name="ExternalAccessible" SystemDefined="true">true</BooleanAttribute><BooleanAttribute Name="ExternalVisible" SystemDefined="true">true</BooleanAttribute><BooleanAttribute Name="ExternalWritable" SystemDefined="true">true</BooleanAttribute><BooleanAttribute Name="SetPoint" SystemDefined="true">true</BooleanAttribute></AttributeList><Sections><Section Name="None"><Member Name="PT" Datatype="Time" /><Member Name="ET" Datatype="Time" /><Member Name="IN" Datatype="Bool" /><Member Name="Q" Datatype="Bool" /></Section></Sections></Member>
    <Member Name="TEFC16" Datatype="TON_TIME" Version="1.0" Remanence="NonRetain" Accessibility="Public"><AttributeList><BooleanAttribute Name="ExternalAccessible" SystemDefined="true">true</BooleanAttribute><BooleanAttribute Name="ExternalVisible" SystemDefined="true">true</BooleanAttribute><BooleanAttribute Name="ExternalWritable" SystemDefined="true">true</BooleanAttribute><BooleanAttribute Name="SetPoint" SystemDefined="true">true</BooleanAttribute></AttributeList><Sections><Section Name="None"><Member Name="PT" Datatype="Time" /><Member Name="ET" Datatype="Time" /><Member Name="IN" Datatype="Bool" /><Member Name="Q" Datatype="Bool" /></Section></Sections></Member>
    <Member Name="TEFC17" Datatype="TON_TIME" Version="1.0" Remanence="NonRetain" Accessibility="Public"><AttributeList><BooleanAttribute Name="ExternalAccessible" SystemDefined="true">true</BooleanAttribute><BooleanAttribute Name="ExternalVisible" SystemDefined="true">true</BooleanAttribute><BooleanAttribute Name="ExternalWritable" SystemDefined="true">true</BooleanAttribute><BooleanAttribute Name="SetPoint" SystemDefined="true">true</BooleanAttribute></AttributeList><Sections><Section Name="None"><Member Name="PT" Datatype="Time" /><Member Name="ET" Datatype="Time" /><Member Name="IN" Datatype="Bool" /><Member Name="Q" Datatype="Bool" /></Section></Sections></Member>
    <Member Name="TEFC18" Datatype="TON_TIME" Version="1.0" Remanence="NonRetain" Accessibility="Public"><AttributeList><BooleanAttribute Name="ExternalAccessible" SystemDefined="true">true</BooleanAttribute><BooleanAttribute Name="ExternalVisible" SystemDefined="true">true</BooleanAttribute><BooleanAttribute Name="ExternalWritable" SystemDefined="true">true</BooleanAttribute><BooleanAttribute Name="SetPoint" SystemDefined="true">true</BooleanAttribute></AttributeList><Sections><Section Name="None"><Member Name="PT" Datatype="Time" /><Member Name="ET" Datatype="Time" /><Member Name="IN" Datatype="Bool" /><Member Name="Q" Datatype="Bool" /></Section></Sections></Member>
    <Member Name="TEFC19" Datatype="TON_TIME" Version="1.0" Remanence="NonRetain" Accessibility="Public"><AttributeList><BooleanAttribute Name="ExternalAccessible" SystemDefined="true">true</BooleanAttribute><BooleanAttribute Name="ExternalVisible" SystemDefined="true">true</BooleanAttribute><BooleanAttribute Name="ExternalWritable" SystemDefined="true">true</BooleanAttribute><BooleanAttribute Name="SetPoint" SystemDefined="true">true</BooleanAttribute></AttributeList><Sections><Section Name="None"><Member Name="PT" Datatype="Time" /><Member Name="ET" Datatype="Time" /><Member Name="IN" Datatype="Bool" /><Member Name="Q" Datatype="Bool" /></Section></Sections></Member>
    <Member Name="TEFC20" Datatype="TON_TIME" Version="1.0" Remanence="NonRetain" Accessibility="Public"><AttributeList><BooleanAttribute Name="ExternalAccessible" SystemDefined="true">true</BooleanAttribute><BooleanAttribute Name="ExternalVisible" SystemDefined="true">true</BooleanAttribute><BooleanAttribute Name="ExternalWritable" SystemDefined="true">true</BooleanAttribute><BooleanAttribute Name="SetPoint" SystemDefined="true">true</BooleanAttribute></AttributeList><Sections><Section Name="None"><Member Name="PT" Datatype="Time" /><Member Name="ET" Datatype="Time" /><Member Name="IN" Datatype="Bool" /><Member Name="Q" Datatype="Bool" /></Section></Sections></Member>
    <Member Name="TEFC21" Datatype="TON_TIME" Version="1.0" Remanence="NonRetain" Accessibility="Public"><AttributeList><BooleanAttribute Name="ExternalAccessible" SystemDefined="true">true</BooleanAttribute><BooleanAttribute Name="ExternalVisible" SystemDefined="true">true</BooleanAttribute><BooleanAttribute Name="ExternalWritable" SystemDefined="true">true</BooleanAttribute><BooleanAttribute Name="SetPoint" SystemDefined="true">true</BooleanAttribute></AttributeList><Sections><Section Name="None"><Member Name="PT" Datatype="Time" /><Member Name="ET" Datatype="Time" /><Member Name="IN" Datatype="Bool" /><Member Name="Q" Datatype="Bool" /></Section></Sections></Member>
    <Member Name="TEFC22" Datatype="TON_TIME" Version="1.0" Remanence="NonRetain" Accessibility="Public"><AttributeList><BooleanAttribute Name="ExternalAccessible" SystemDefined="true">true</BooleanAttribute><BooleanAttribute Name="ExternalVisible" SystemDefined="true">true</BooleanAttribute><BooleanAttribute Name="ExternalWritable" SystemDefined="true">true</BooleanAttribute><BooleanAttribute Name="SetPoint" SystemDefined="true">true</BooleanAttribute></AttributeList><Sections><Section Name="None"><Member Name="PT" Datatype="Time" /><Member Name="ET" Datatype="Time" /><Member Name="IN" Datatype="Bool" /><Member Name="Q" Datatype="Bool" /></Section></Sections></Member>
    <Member Name="TEFC23" Datatype="TON_TIME" Version="1.0" Remanence="NonRetain" Accessibility="Public"><AttributeList><BooleanAttribute Name="ExternalAccessible" SystemDefined="true">true</BooleanAttribute><BooleanAttribute Name="ExternalVisible" SystemDefined="true">true</BooleanAttribute><BooleanAttribute Name="ExternalWritable" SystemDefined="true">true</BooleanAttribute><BooleanAttribute Name="SetPoint" SystemDefined="true">true</BooleanAttribute></AttributeList><Sections><Section Name="None"><Member Name="PT" Datatype="Time" /><Member Name="ET" Datatype="Time" /><Member Name="IN" Datatype="Bool" /><Member Name="Q" Datatype="Bool" /></Section></Sections></Member>
    <Member Name="TEFC24" Datatype="TON_TIME" Version="1.0" Remanence="NonRetain" Accessibility="Public"><AttributeList><BooleanAttribute Name="ExternalAccessible" SystemDefined="true">true</BooleanAttribute><BooleanAttribute Name="ExternalVisible" SystemDefined="true">true</BooleanAttribute><BooleanAttribute Name="ExternalWritable" SystemDefined="true">true</BooleanAttribute><BooleanAttribute Name="SetPoint" SystemDefined="true">true</BooleanAttribute></AttributeList><Sections><Section Name="None"><Member Name="PT" Datatype="Time" /><Member Name="ET" Datatype="Time" /><Member Name="IN" Datatype="Bool" /><Member Name="Q" Datatype="Bool" /></Section></Sections></Member>
    <Member Name="TEFC25" Datatype="TON_TIME" Version="1.0" Remanence="NonRetain" Accessibility="Public"><AttributeList><BooleanAttribute Name="ExternalAccessible" SystemDefined="true">true</BooleanAttribute><BooleanAttribute Name="ExternalVisible" SystemDefined="true">true</BooleanAttribute><BooleanAttribute Name="ExternalWritable" SystemDefined="true">true</BooleanAttribute><BooleanAttribute Name="SetPoint" SystemDefined="true">true</BooleanAttribute></AttributeList><Sections><Section Name="None"><Member Name="PT" Datatype="Time" /><Member Name="ET" Datatype="Time" /><Member Name="IN" Datatype="Bool" /><Member Name="Q" Datatype="Bool" /></Section></Sections></Member>
    <Member Name="TEFC26" Datatype="TON_TIME" Version="1.0" Remanence="NonRetain" Accessibility="Public"><AttributeList><BooleanAttribute Name="ExternalAccessible" SystemDefined="true">true</BooleanAttribute><BooleanAttribute Name="ExternalVisible" SystemDefined="true">true</BooleanAttribute><BooleanAttribute Name="ExternalWritable" SystemDefined="true">true</BooleanAttribute><BooleanAttribute Name="SetPoint" SystemDefined="true">true</BooleanAttribute></AttributeList><Sections><Section Name="None"><Member Name="PT" Datatype="Time" /><Member Name="ET" Datatype="Time" /><Member Name="IN" Datatype="Bool" /><Member Name="Q" Datatype="Bool" /></Section></Sections></Member>
    <Member Name="TEFC27" Datatype="TON_TIME" Version="1.0" Remanence="NonRetain" Accessibility="Public"><AttributeList><BooleanAttribute Name="ExternalAccessible" SystemDefined="true">true</BooleanAttribute><BooleanAttribute Name="ExternalVisible" SystemDefined="true">true</BooleanAttribute><BooleanAttribute Name="ExternalWritable" SystemDefined="true">true</BooleanAttribute><BooleanAttribute Name="SetPoint" SystemDefined="true">true</BooleanAttribute></AttributeList><Sections><Section Name="None"><Member Name="PT" Datatype="Time" /><Member Name="ET" Datatype="Time" /><Member Name="IN" Datatype="Bool" /><Member Name="Q" Datatype="Bool" /></Section></Sections></Member>
    <Member Name="TEFC28" Datatype="TON_TIME" Version="1.0" Remanence="NonRetain" Accessibility="Public"><AttributeList><BooleanAttribute Name="ExternalAccessible" SystemDefined="true">true</BooleanAttribute><BooleanAttribute Name="ExternalVisible" SystemDefined="true">true</BooleanAttribute><BooleanAttribute Name="ExternalWritable" SystemDefined="true">true</BooleanAttribute><BooleanAttribute Name="SetPoint" SystemDefined="true">true</BooleanAttribute></AttributeList><Sections><Section Name="None"><Member Name="PT" Datatype="Time" /><Member Name="ET" Datatype="Time" /><Member Name="IN" Datatype="Bool" /><Member Name="Q" Datatype="Bool" /></Section></Sections></Member>
  </Section>
</Sections></Interface>
      <Name>MODBUS_DB</Name>
      <Number>102</Number>
      <ProgrammingLanguage>DB</ProgrammingLanguage>
    </AttributeList>
    <ObjectList>
      <MultilingualText ID="1" CompositionName="Comment">
        <ObjectList>
          <MultilingualTextItem ID="2" CompositionName="Items">
            <AttributeList>
              <Culture>en-US</Culture>
              <Text />
            </AttributeList>
          </MultilingualTextItem>
          <MultilingualTextItem ID="3" CompositionName="Items">
            <AttributeList>
              <Culture>pt-BR</Culture>
              <Text />
            </AttributeList>
          </MultilingualTextItem>
        </ObjectList>
      </MultilingualText>
      <MultilingualText ID="4" CompositionName="Title">
        <ObjectList>
          <MultilingualTextItem ID="5" CompositionName="Items">
            <AttributeList>
              <Culture>en-US</Culture>
              <Text />
            </AttributeList>
          </MultilingualTextItem>
          <MultilingualTextItem ID="6" CompositionName="Items">
            <AttributeList>
              <Culture>pt-BR</Culture>
              <Text />
            </AttributeList>
          </MultilingualTextItem>
        </ObjectList>
      </MultilingualText>
    </ObjectList>
  </SW.Blocks.InstanceDB>
</Document>